odoo/addons/website_sale_default_country/README.rst
odoo/addons/website_sale_default_country/__init__.py
odoo/addons/website_sale_default_country/__manifest__.py
odoo/addons/website_sale_default_country/controllers/__init__.py
odoo/addons/website_sale_default_country/controllers/main.py
odoo/addons/website_sale_default_country/static/description/icon.png
odoo11_addon_website_sale_default_country-11.0.1.0.0.dist-info/DESCRIPTION.rst
odoo11_addon_website_sale_default_country-11.0.1.0.0.dist-info/METADATA
odoo11_addon_website_sale_default_country-11.0.1.0.0.dist-info/RECORD
odoo11_addon_website_sale_default_country-11.0.1.0.0.dist-info/WHEEL
odoo11_addon_website_sale_default_country-11.0.1.0.0.dist-info/metadata.json
odoo11_addon_website_sale_default_country-11.0.1.0.0.dist-info/top_level.txt
